<annotation>
	<folder>image</folder>
	<filename>3035.jpg</filename>
	<path>C:\Users\wldnj\Desktop\Real-time-image-based-obstacle-detection-and-identification-system-using-deep-learning-on-railroad\video\image\3035.jpg</path>
	<source>
		<database>Unknown</database>
	</source>
	<size>
		<width>1371</width>
		<height>749</height>
		<depth>3</depth>
	</size>
	<segmented>0</segmented>
	<object>
		<name>people</name>
		<pose>Unspecified</pose>
		<truncated>0</truncated>
		<difficult>0</difficult>
		<bndbox>
			<xmin>1027</xmin>
			<ymin>79</ymin>
			<xmax>1101</xmax>
			<ymax>289</ymax>
		</bndbox>
	</object>
</annotation>
