<annotation>
	<folder>image</folder>
	<filename>513.jpg</filename>
	<path>C:\Users\김민석\Desktop\Railway_Obstacle_Detection\others\new video\image\513.jpg</path>
	<source>
		<database>Unknown</database>
	</source>
	<size>
		<width>1920</width>
		<height>1080</height>
		<depth>3</depth>
	</size>
	<segmented>0</segmented>
	<object>
		<name>tree</name>
		<pose>Unspecified</pose>
		<truncated>0</truncated>
		<difficult>0</difficult>
		<bndbox>
			<xmin>564</xmin>
			<ymin>129</ymin>
			<xmax>801</xmax>
			<ymax>538</ymax>
		</bndbox>
	</object>
	<object>
		<name>tree</name>
		<pose>Unspecified</pose>
		<truncated>0</truncated>
		<difficult>0</difficult>
		<bndbox>
			<xmin>70</xmin>
			<ymin>315</ymin>
			<xmax>114</xmax>
			<ymax>424</ymax>
		</bndbox>
	</object>
</annotation>
