<annotation>
	<folder>train</folder>
	<filename>79.jpg</filename>
	<path>C:\Users\김민석\Desktop\Real-time image-based obstacle detection and identification system using deep learning on railroad tracks environments\obstacle_detection\train\79.jpg</path>
	<source>
		<database>Unknown</database>
	</source>
	<size>
		<width>1280</width>
		<height>720</height>
		<depth>3</depth>
	</size>
	<segmented>0</segmented>
	<object>
		<name>people</name>
		<pose>Unspecified</pose>
		<truncated>1</truncated>
		<difficult>0</difficult>
		<bndbox>
			<xmin>695</xmin>
			<ymin>1</ymin>
			<xmax>1194</xmax>
			<ymax>348</ymax>
		</bndbox>
	</object>
</annotation>
